{
    "key": "group_660437b8bd83f",
    "title": "News Settings",
    "fields": [
        {
            "key": "field_660438525457e",
            "label": "News Subtitle",
            "name": "news_subtitle",
            "aria-label": "",
            "type": "textarea",
            "instructions": "",
            "required": 0,
            "conditional_logic": 0,
            "wrapper": {
                "width": "",
                "class": "",
                "id": ""
            },
            "default_value": "",
            "maxlength": "",
            "rows": 3,
            "placeholder": "",
            "new_lines": "br",
            "wpml_cf_preferences": 2
        },
        {
            "key": "field_660437b95457b",
            "label": "News Content Type",
            "name": "news_content_type",
            "aria-label": "",
            "type": "select",
            "instructions": "",
            "required": 0,
            "conditional_logic": 0,
            "wrapper": {
                "width": "",
                "class": "",
                "id": ""
            },
            "wpml_cf_preferences": 3,
            "choices": {
                "internal": "Internal Page",
                "external": "External Link"
            },
            "default_value": "internal",
            "return_format": "value",
            "multiple": 0,
            "allow_null": 0,
            "ui": 0,
            "ajax": 0,
            "placeholder": ""
        },
        {
            "key": "field_660437ef5457c",
            "label": "External URL",
            "name": "external_url",
            "aria-label": "",
            "type": "url",
            "instructions": "",
            "required": 0,
            "conditional_logic": [
                [
                    {
                        "field": "field_660437b95457b",
                        "operator": "==",
                        "value": "external"
                    }
                ]
            ],
            "wrapper": {
                "width": "",
                "class": "",
                "id": ""
            },
            "wpml_cf_preferences": 2,
            "default_value": "",
            "placeholder": ""
        },
        {
            "key": "field_660438ab5457f",
            "label": "Press Location",
            "name": "press_location",
            "aria-label": "",
            "type": "text",
            "instructions": "",
            "required": 0,
            "conditional_logic": [
                [
                    {
                        "field": "field_660437b95457b",
                        "operator": "==",
                        "value": "internal"
                    }
                ]
            ],
            "wrapper": {
                "width": "",
                "class": "",
                "id": ""
            },
            "default_value": "",
            "maxlength": "",
            "placeholder": "",
            "prepend": "",
            "append": "",
            "wpml_cf_preferences": 2
        },
        {
            "key": "field_660438215457d",
            "label": "Press Content",
            "name": "press_content",
            "aria-label": "",
            "type": "wysiwyg",
            "instructions": "",
            "required": 0,
            "conditional_logic": [
                [
                    {
                        "field": "field_660437b95457b",
                        "operator": "==",
                        "value": "internal"
                    }
                ]
            ],
            "wrapper": {
                "width": "",
                "class": "",
                "id": ""
            },
            "default_value": "",
            "tabs": "all",
            "toolbar": "full",
            "media_upload": 1,
            "delay": 0,
            "wpml_cf_preferences": 2
        },
        {
            "key": "field_6604395b54580",
            "label": "Press Contact Information",
            "name": "press_contact_information",
            "aria-label": "",
            "type": "wysiwyg",
            "instructions": "",
            "required": 0,
            "conditional_logic": [
                [
                    {
                        "field": "field_660437b95457b",
                        "operator": "==",
                        "value": "internal"
                    }
                ]
            ],
            "wrapper": {
                "width": "",
                "class": "",
                "id": ""
            },
            "default_value": "",
            "tabs": "all",
            "toolbar": "full",
            "media_upload": 0,
            "delay": 0,
            "wpml_cf_preferences": 2
        }
    ],
    "location": [
        [
            {
                "param": "post_type",
                "operator": "==",
                "value": "news"
            }
        ]
    ],
    "menu_order": 0,
    "position": "acf_after_title",
    "style": "default",
    "label_placement": "top",
    "instruction_placement": "label",
    "hide_on_screen": [
        "the_content",
        "excerpt",
        "discussion",
        "comments",
        "author",
        "format",
        "page_attributes"
    ],
    "active": true,
    "description": "",
    "show_in_rest": 0,
    "acfml_field_group_mode": "advanced",
    "modified": 1714490646
}
