{
    "key": "group_65ef2c2f81096",
    "title": "Glossary Term",
    "fields": [
        {
            "key": "field_65ef3fb4403be",
            "label": "Glossary Term Headline",
            "name": "glossary_term_headline",
            "aria-label": "",
            "type": "text",
            "instructions": "",
            "required": 0,
            "conditional_logic": 0,
            "wrapper": {
                "width": "",
                "class": "",
                "id": ""
            },
            "default_value": "",
            "maxlength": "",
            "placeholder": "",
            "prepend": "",
            "append": "",
            "wpml_cf_preferences": 2
        },
        {
            "key": "field_65ef2c2fd34b0",
            "label": "Include Table of Contents",
            "name": "include_table_of_contents",
            "aria-label": "",
            "type": "select",
            "instructions": "",
            "required": 0,
            "conditional_logic": 0,
            "wrapper": {
                "width": "",
                "class": "",
                "id": ""
            },
            "wpml_cf_preferences": 3,
            "choices": {
                "show": "Show",
                "hide": "Hide"
            },
            "default_value": "show",
            "return_format": "value",
            "multiple": 0,
            "allow_null": 0,
            "ui": 0,
            "ajax": 0,
            "placeholder": ""
        },
        {
            "key": "field_65ef2c70d34b1",
            "label": "Related Terms",
            "name": "related_terms",
            "aria-label": "",
            "type": "post_object",
            "instructions": "",
            "required": 0,
            "conditional_logic": 0,
            "wrapper": {
                "width": "",
                "class": "",
                "id": ""
            },
            "wpml_cf_preferences": 3,
            "post_type": [
                "glossary"
            ],
            "post_status": [
                "publish"
            ],
            "taxonomy": "",
            "return_format": "object",
            "multiple": 1,
            "allow_null": 0,
            "bidirectional": 0,
            "ui": 1,
            "bidirectional_target": []
        }
    ],
    "location": [
        [
            {
                "param": "post_type",
                "operator": "==",
                "value": "glossary"
            }
        ]
    ],
    "menu_order": 0,
    "position": "normal",
    "style": "default",
    "label_placement": "top",
    "instruction_placement": "label",
    "hide_on_screen": "",
    "active": true,
    "description": "",
    "show_in_rest": 0,
    "acfml_field_group_mode": "advanced",
    "modified": 1714058717
}
